.gitignore
CHANGELOG.md
LICENSE
MANIFEST.in
README.rst
requirements.txt
setup.py
bless_deployer/__init__.py
bless_deployer/__main__.py
bless_deployer/utils.py
bless_deployer.egg-info/PKG-INFO
bless_deployer.egg-info/SOURCES.txt
bless_deployer.egg-info/dependency_links.txt
bless_deployer.egg-info/entry_points.txt
bless_deployer.egg-info/not-zip-safe
bless_deployer.egg-info/pbr.json
bless_deployer.egg-info/requires.txt
bless_deployer.egg-info/top_level.txt
bless_deployer/data/deploy.cfg